Metadata-Version: 1.0
Name: charlypkg
Version: 0.2
Summary: First python package ever created by me.
Home-page: http://github.com/antunescarles/charlypkg
Author: Carlos Antunes
Author-email: antunes.p.carlos@hotmail.com
License: MIT
Platform: UNKNOWN
